tkmvc/__init__.py
tkmvc/cli.py
tkmvc/tkmvc.py
tkmvc/controllers/__init__.py
tkmvc/controllers/controller.py
tkmvc/models/__init__.py
tkmvc/models/bank_model.py
tkmvc/models/customer_model.py
tkmvc/models/teller_model.py
tkmvc/views/__init__.py
tkmvc/views/bank_view.py
tkmvc/views/customer_view.py
tkmvc/views/teller_view.py
tkmvc-0.1.28.dist-info/AUTHORS.rst
tkmvc-0.1.28.dist-info/LICENSE
tkmvc-0.1.28.dist-info/METADATA
tkmvc-0.1.28.dist-info/WHEEL
tkmvc-0.1.28.dist-info/entry_points.txt
tkmvc-0.1.28.dist-info/top_level.txt
tkmvc-0.1.28.dist-info/RECORD
