Metadata-Version: 2.1
Name: tkmvc
Version: 0.1.28
Summary: TkMVC is a Model-View-Controller Framework base on the Tkinter GUI toolkit.
Home-page: https://github.com/unodan/tkmvc
Author: Dan Huckson
Author-email: danhuckson@hotmail.com
License: MIT license
Keywords: tkmvc
Platform: UNKNOWN
Classifier: Development Status :: 2 - Pre-Alpha
Classifier: Intended Audience :: Developers
Classifier: License :: OSI Approved :: MIT License
Classifier: Natural Language :: English
Classifier: Programming Language :: Python :: 2
Classifier: Programming Language :: Python :: 2.7
Classifier: Programming Language :: Python :: 3
Classifier: Programming Language :: Python :: 3.4
Classifier: Programming Language :: Python :: 3.5
Classifier: Programming Language :: Python :: 3.6
Classifier: Programming Language :: Python :: 3.7
Requires-Dist: Click (>=6.0)
